zeph1rr_fastapi_utils/__init__.py
zeph1rr_fastapi_utils/logger.py
zeph1rr_fastapi_utils/utils.py
zeph1rr_fastapi_utils-1.1.0.dist-info/METADATA
zeph1rr_fastapi_utils-1.1.0.dist-info/WHEEL
zeph1rr_fastapi_utils-1.1.0.dist-info/RECORD
