Metadata-Version: 2.1
Name: zeph1rr-fastapi-utils
Version: 1.1.0
Summary: Package for unificate functions in fastapi
Author: Zeph1rr
Author-email: grianton535@gmail.com
Requires-Python: >=3.11,<4.0
Classifier: Programming Language :: Python :: 3
Classifier: Programming Language :: Python :: 3.11
Requires-Dist: bcrypt (>=4.0.1,<5.0.0)
Requires-Dist: fastapi (>=0.95.2,<0.96.0)
Requires-Dist: loguru (>=0.7.0,<0.8.0)
Requires-Dist: passlib (>=1.7.4,<2.0.0)
Requires-Dist: pydantic (>=1.10.8,<2.0.0)
Requires-Dist: python-jose (>=3.3.0,<4.0.0)
Requires-Dist: tomli (>=2.0.1,<3.0.0)
